PhantomDecode.py
phantomdecode-1.0.dist-info/LICENSE
phantomdecode-1.0.dist-info/METADATA
phantomdecode-1.0.dist-info/WHEEL
phantomdecode-1.0.dist-info/RECORD
