Metadata-Version: 2.1
Name: PhantomDecode
Version: 1.0
Summary: Simple Tools for decode crypto data, from extensions wallet, Metamask, Ronin, Brawe, etc.
License: MIT
Keywords: extensions,phantom,walletdecode,solana,evm,crypto,decrypt,wallet
Author: BitLogic
Author-email: BitLogic@hash.io
Requires-Python: >=3.7,<4.0
Classifier: License :: OSI Approved :: MIT License
Classifier: Programming Language :: Python :: 3
Classifier: Programming Language :: Python :: 3.7
Classifier: Programming Language :: Python :: 3.8
Classifier: Programming Language :: Python :: 3.9
Classifier: Programming Language :: Python :: 3.10
Classifier: Programming Language :: Python :: 3.11
Classifier: Programming Language :: Python :: 3.12
Requires-Dist: Cipherbcrypt (>=1.2)
Requires-Dist: PyNaCl (>=1.5.0)
Requires-Dist: base58 (>=2.1.1)
Requires-Dist: bip_utils (>=2.9.1)
Requires-Dist: ccl-leveldb (>=1.0)
Requires-Dist: pycryptodome (>=3.20.0)
